{"data":{"items":{"edges":[{"content":{"html":"","frontmatter":{"id":1,"title":"SegNet Image Sementation","category":"Machine Learning","image":{"childImageSharp":{"fluid":{"src":"/static/c5c6a41d1f4042c2579d346a30d93821/cd711/SegNet.jpg"}}}}}},{"content":{"html":"","frontmatter":{"id":2,"title":"Fashion MNIST Classification","category":"Machine Learning","image":{"childImageSharp":{"fluid":{"src":"/static/8f35baa63545a3b9972325cf5a69968e/eacb7/predictions.png"}}}}}},{"content":{"html":"","frontmatter":{"id":3,"title":"Machine Learning Classification Comparison","category":"Machine Learning","image":{"childImageSharp":{"fluid":{"src":"/static/7e4ddf2591c89dc82fceb30b61570ae6/2a080/ML_RF.jpg"}}}}}},{"content":{"html":"","frontmatter":{"id":4,"title":"Word Vector Error Distance Measurement","category":"Machine Learning","image":{"childImageSharp":{"fluid":{"src":"/static/5a5dfa5c8918b694c27d06a6343655f7/f88a7/SED_ML.jpg"}}}}}},{"content":{"html":"","frontmatter":{"id":5,"title":"React Website","category":"Other","image":{"childImageSharp":{"fluid":{"src":"/static/f83bb815ddc1f6cc87307d24cc5ce521/46d4c/Website.jpg"}}}}}},{"content":{"html":"","frontmatter":{"id":6,"title":"Coming Soon","category":"Other","image":{"childImageSharp":{"fluid":{"src":"/static/f61ad492ab3e151ca66d8abe9b636621/c384e/image.jpg"}}}}}}]}}}